cetl/__init__.py
cetl/dev_tests/__init__.py
cetl/dev_tests/sample10_test_parallel_at_beginning.py
cetl/dev_tests/sample11_adding_kafka_media.py
cetl/dev_tests/sample12_test_dummyStartEmpty.py
cetl/dev_tests/sample1_test_for_pipeline_v1.py
cetl/dev_tests/sample2_test_for_pipeline_v1.py
cetl/dev_tests/sample3_test_for_pipeline_v2.py
cetl/dev_tests/sample4_test_for_pipeline_v3.py
cetl/dev_tests/sample5_data_container_type.py
cetl/dev_tests/sample6_build_pipeline.py
cetl/dev_tests/sample7_build_pipeline_from_cfg.py
cetl/dev_tests/sample8_build_pipeline.py
cetl/dev_tests/sample9_build_pipeline_from_cfg2.py
cetl/functional_modules/__init__.py
cetl/functional_modules/dummy_transformer.py
cetl/functional_modules/multithread_transformers.py
cetl/functional_modules/parallel_transformer.py
cetl/functional_modules/pass_dataframe.py
cetl/json_modules/__init__.py
cetl/json_modules/drop_columns.py
cetl/json_modules/input.py
cetl/pandas_modules/__init__.py
cetl/pandas_modules/add_new_column.py
cetl/pandas_modules/add_row_number.py
cetl/pandas_modules/dataframe_mgt.py
cetl/pandas_modules/filter.py
cetl/pandas_modules/input.py
cetl/pandas_modules/pass_dataframe.py
cetl/pandas_modules/two2one.py
cetl/spark_modules/__init__.py
cetl/sqlalchemy_modules/__init__.py
cetl/utils/__init__.py
cetl/utils/airflow_pipeline.py
cetl/utils/base.py
cetl/utils/block.py
cetl/utils/builder.py
cetl/utils/dataframe.py
cetl/utils/dot_node.py
cetl/utils/encryption.py
cetl/utils/file_mgt.py
cetl/utils/formating.py
cetl/utils/kafka.py
cetl/utils/kafka_helper.py
cetl/utils/kafka_media.py
cetl/utils/pipeline.py
cetl/utils/registry.py
cetl/utils/samplings.py
cetl/utils/sftp_file_mgt.py
cetl/utils/transform_wrapper.py
sample_user_project/__init__.py
sample_user_project/app.py
sample_user_project/call_api.py
sample_user_project/compress_files.py
sample_user_project/test_file_compress.py
sample_user_project/file_modules/__init__.py
sample_user_project/file_modules/builder.py
cetl-0.3.0.dist-info/LICENSE
cetl-0.3.0.dist-info/METADATA
cetl-0.3.0.dist-info/WHEEL
cetl-0.3.0.dist-info/top_level.txt
cetl-0.3.0.dist-info/RECORD
