Metadata-Version: 2.1
Name: cetl
Version: 0.3.0
Summary: A basic data pipeline tools for data engineer to handle the CRM or loyalty data
Author: Clement
Author-email: <cheukub@gmail.com>
Keywords: python,data pipeline,pipeline
Classifier: Development Status :: 1 - Planning
Classifier: Intended Audience :: Developers
Classifier: Programming Language :: Python :: 3
Classifier: Operating System :: POSIX :: Linux
License-File: LICENSE
Requires-Dist: flask
Requires-Dist: SQLalchemy
Requires-Dist: pyspark
Requires-Dist: pandas
